Pequena/__init__.py
Pequena/api.py
Pequena/window.py
Pequena-0.0.58.dist-info/LICENSE
Pequena-0.0.58.dist-info/METADATA
Pequena-0.0.58.dist-info/WHEEL
Pequena-0.0.58.dist-info/top_level.txt
Pequena-0.0.58.dist-info/RECORD
